jsonapi/__init__.py
jsonapi/_jsonapi.py
jsonapi/tests.py
jsonapi_simple-0.2.2.dist-info/LICENSE
jsonapi_simple-0.2.2.dist-info/METADATA
jsonapi_simple-0.2.2.dist-info/WHEEL
jsonapi_simple-0.2.2.dist-info/top_level.txt
jsonapi_simple-0.2.2.dist-info/RECORD
