Metadata-Version: 2.1
Name: jsonapi-simple
Version: 0.2.2
Summary: A minimalistic JSON API framework in Python with support for graphql-style queries.
Home-page: https://github.com/apiad/jsonapi
Author: Alejandro Piad
Author-email: apiad@apiad.net
License: UNKNOWN
Platform: UNKNOWN
Classifier: Programming Language :: Python :: 3.5
Classifier: Programming Language :: Python :: 3.6
Classifier: License :: OSI Approved :: MIT License
Classifier: Operating System :: OS Independent
